{
	"type": "background",
	"name": {
		"primary": "Thrill-Seeker"
	},
	"source": {
		"page": 75,
		"ID": "LOFb"
	},
	"data": {
		"entries": [
			"You once survived a life-or-death situation and found it surprisingly exhilarating, so now you chase that feeling of invincibility you only get when dancing with death. Your desire for exhilaration has you scaling buildings, leaping off rooftops, jumping chasms, and performing other deathdefying stunts.",
			"Choose two ability boosts. One must be to Strength or Constitution, and one is a free ability boost.",
			"You are trained in the {@skill Athletics} skill and the {@skill Lore||Engineering Lore} skill. You gain the {@feat Combat Climber} skill feat."
		]
	},
	"tags": {
		"abilityBoosts": {
			"count": 2,
			"abilities": {
				"strength": true,
				"constitution": true,
				"free": true
			}
		},
		"trainedSkills": {
			"count": 2,
			"skills": {
				"Athletics": true,
				"Lore": true
			}
		},
		"gainedFeats": {
			"count": 1,
			"options": [
				{
					"name": "Combat Climber",
					"sourceID": "CRB"
				}
			]
		}
	}
}
