{"Glamered|CRB|":"data/core/Core Rulebook/relicGift/Glamered.json","Energy-Resistant|CRB|Electricity":"data/core/Core Rulebook/relicGift/Energy-Resistant - Electricity.json","Lightning Storm|GMG|":"data/core/Gamemastery Guide/relicGift/Lightning Storm.json","Tajarka|SolthesiaAG|":"data/homebrew/Solthesia Adventure Guide/divineIntercession/Tajarka.json","Concordance Scout|RoE|":"data/core/Rage of Elements/background/Concordance Scout.json","Whammy|TV|":"data/core/Treasure Vault/relicGift/Whammy.json","Planar Migrant|RoE|":"data/core/Rage of Elements/background/Planar Migrant.json","Strixwind Race|LOTG|":"data/core/Lost Omens_ Travel Guide/event/Strixwind Race.json","Brevic Noble|KmrA|":"data/core/Kingmaker/background/Brevic Noble.json","Invisible|CRB|":"data/core/Core Rulebook/condition/Invisible.json","Sanguine Cascade|LOTG|":"data/core/Lost Omens_ Travel Guide/event/Sanguine Cascade.json","Ex-Mendevian Crusader|QFF0|":"data/core/Quest for the Frozen Flame Player's Guide/background/Ex-Mendevian Crusader.json","Fleeing|CRB|":"data/core/Core Rulebook/condition/Fleeing.json","Fortune Teller|CRB|":"data/core/Core Rulebook/background/Fortune Teller.json","Animal Whisperer|CRB|":"data/core/Core Rulebook/background/Animal Whisperer.json","Propaganda Promoter|BL0|":"data/core/Blood Lords Player's Guide/background/Propaganda Promoter.json","Grand Council Bureaucrat|LOWG|":"data/core/Lost Omens_ World Guide/background/Grand Council Bureaucrat.json","Sarenrae|LOGM|":"data/core/Lost Omens_ Gods & Magic/divineIntercession/Sarenrae.json","Greater Disrupting|CRB|":"data/core/Core Rulebook/relicGift/Greater Disrupting.json","Word of Faith|GMG|":"data/core/Gamemastery Guide/relicGift/Word of Faith.json","Pharasma|LOGM|":"data/core/Lost Omens_ Gods & Magic/divineIntercession/Pharasma.json","Greater Energy-Resistant|CRB|Cold":"data/core/Core Rulebook/relicGift/Greater Energy-Resistant - Cold.json","Sprout Ally|GMG|":"data/core/Gamemastery Guide/relicGift/Sprout Ally.json","Iomedae|LOGM|":"data/core/Lost Omens_ Gods & Magic/divineIntercession/Iomedae.json","Dark Roads|GMG|":"data/core/Gamemastery Guide/relicGift/Dark Roads.json","Gozreh|LOGM|":"data/core/Lost Omens_ Gods & Magic/divineIntercession/Gozreh.json","Sentinel Reflectance|LOKL|":"data/core/Lost Omens_ Knights of Lastwall/background/Sentinel Reflectance.json","Concealed|CRB|":"data/core/Core Rulebook/condition/Concealed.json","Relentless Dedication|LOKL|":"data/core/Lost Omens_ Knights of Lastwall/background/Relentless Dedication.json","Living Forge|LOHh|":"data/core/Lost Omens_ Highhelm/relicGift/Living Forge.json","Blessed|APG|":"data/core/Advanced Player's Guide/background/Blessed.json","Attention Addict|FRP0|":"data/core/Fists of the Ruby Phoenix Player's Guide/background/Attention Addict.json","Unconscious|CRB|":"data/core/Core Rulebook/condition/Unconscious.json","Ramuniandanjara|SolthesiaAG|":"data/homebrew/Solthesia Adventure Guide/divineIntercession/Ramuniandanjara.json","Hired Killer|GaG|":"data/core/Guns & Gears/background/Hired Killer.json","Perception Filter|GMG|":"data/core/Gamemastery Guide/relicGift/Perception Filter.json","Urgathoa|LOGM|":"data/core/Lost Omens_ Gods & Magic/divineIntercession/Urgathoa.json","Wandering Preacher|GaG|":"data/core/Guns & Gears/background/Wandering Preacher.json","Sally Guard Neophyte|AoE0|":"data/core/Agents of Edgewatch Player's Guide/background/Sally Guard Neophyte.json","Haunted|APG|":"data/core/Advanced Player's Guide/background/Haunted.json","Root Worker|APG|":"data/core/Advanced Player's Guide/background/Root Worker.json","Energy-Resistant|CRB|Cold":"data/core/Core Rulebook/relicGift/Energy-Resistant - Cold.json","Zekets|SolthesiaAG|":"data/homebrew/Solthesia Adventure Guide/divineIntercession/Zekets.json","Feral Claws|GMG|":"data/core/Gamemastery Guide/relicGift/Feral Claws.json","Cultist|APG|":"data/core/Advanced Player's Guide/background/Cultist.json","Dragon Strike|SoM|":"data/core/Secrets of Magic/relicGift/Dragon Strike.json","Taldan Schemer|LOWG|":"data/core/Lost Omens_ World Guide/background/Taldan Schemer.json","Shoanti Name-bearer|LOWG|":"data/core/Lost Omens_ World Guide/background/Shoanti Name-bearer.json","Legacy of the Hammer|DA|":"data/core/Dark Archive/background/Legacy of the Hammer.json","Living Death|GMG|":"data/core/Gamemastery Guide/relicGift/Living Death.json","Clockfighter|GaG|":"data/core/Guns & Gears/background/Clockfighter.json","Clown|EC0|":"data/core/Extinction Curse Player's Guide/background/Clown.json","Asmodeus|LOGM|":"data/core/Lost Omens_ Gods & Magic/divineIntercession/Asmodeus.json","Sarkoris Scab|LOTG|":"data/core/Lost Omens_ Travel Guide/event/Sarkoris Scab.json","Rostland Partisan|LOWG|":"data/core/Lost Omens_ World Guide/background/Rostland Partisan.json","Greater Slick|CRB|":"data/core/Core Rulebook/relicGift/Greater Slick.json","Stupefied|CRB|":"data/core/Core Rulebook/condition/Stupefied.json","Broken Tusk Recruiter|QFF0|":"data/core/Quest for the Frozen Flame Player's Guide/background/Broken Tusk Recruiter.json","Undetected|CRB|":"data/core/Core Rulebook/condition/Undetected.json","Chosen One|SoM|":"data/core/Secrets of Magic/background/Chosen One.json","Grandmother Spider|LOGM-WS|":"data/core/Lost Omens_ Gods & Magic Web Supplement/divineIntercession/Grandmother Spider.json","Emissary|CRB|":"data/core/Core Rulebook/background/Emissary.json","Scavenger|APG|":"data/core/Advanced Player's Guide/background/Scavenger.json","Occult Librarian|SoM|":"data/core/Secrets of Magic/background/Occult Librarian.json","Freed Slave Of Absalom|LOWG|":"data/core/Lost Omens_ World Guide/background/Freed Slave Of Absalom.json","Arcana|CRB|":"data/core/Core Rulebook/skill/Arcana.json","Enhancing Circuitry|RoE|":"data/core/Rage of Elements/relicGift/Enhancing Circuitry.json","Mantis Scion|LOWG|":"data/core/Lost Omens_ World Guide/background/Mantis Scion.json","Religion|CRB|":"data/core/Core Rulebook/skill/Religion.json","Paralyzed|CRB|":"data/core/Core Rulebook/condition/Paralyzed.json","Medicine|CRB|":"data/core/Core Rulebook/skill/Medicine.json","Senghor Sailor|LOWG|":"data/core/Lost Omens_ World Guide/background/Senghor Sailor.json","Flaming|CRB|":"data/core/Core Rulebook/relicGift/Flaming.json","Sarkorian Reclaimer|LOWG|":"data/core/Lost Omens_ World Guide/background/Sarkorian Reclaimer.json","Heaven's Grace|GMG|":"data/core/Gamemastery Guide/relicGift/Heaven's Grace.json","Songsinger in Training|QFF0|":"data/core/Quest for the Frozen Flame Player's Guide/background/Songsinger in Training.json","Hermean Expatriate|LOWG|":"data/core/Lost Omens_ World Guide/background/Hermean Expatriate.json","Hermean Heritor|AoA6|":"data/core/Age of Ashes #6_ Broken Promises/background/Hermean Heritor.json","Repository of Knowledge|GMG|":"data/core/Gamemastery Guide/relicGift/Repository of Knowledge.json","Awful Scab|C-WtD1|":"data/core/Wake the Dead #1/background/Awful Scab.json","Truth Seeker|AoA0|":"data/core/Age of Ashes Player's Guide/background/Truth Seeker.json","Spirit Blink|SoM|":"data/core/Secrets of Magic/relicGift/Spirit Blink.json","Junker|GaG|":"data/core/Guns & Gears/background/Junker.json","Outskirt Dweller|SoG0|":"data/core/Season of Ghosts Player's Guide/background/Outskirt Dweller.json","Barkeep|CRB|":"data/core/Core Rulebook/background/Barkeep.json","Society|CRB|":"data/core/Core Rulebook/skill/Society.json","Grave Robber|BotD|":"data/core/Book of the Dead/background/Grave Robber.json","Geb Crusader|LOWG|":"data/core/Lost Omens_ World Guide/background/Geb Crusader.json","Zon-Kuthon|LOGM|":"data/core/Lost Omens_ Gods & Magic/divineIntercession/Zon-Kuthon.json","Thrill-Seeker|LOFb|":"data/core/Lost Omens_ Firebrands/background/Thrill-Seeker.json","Apothecary's Garden|GMG|":"data/core/Gamemastery Guide/relicGift/Apothecary's Garden.json","Lightning Dancing|LOTG|":"data/core/Lost Omens_ Travel Guide/event/Lightning Dancing.json","Fascinating|TV|":"data/core/Treasure Vault/relicGift/Fascinating.json","Hookclaw Digger|LTiBA-PSSD|":"data/core/Little Trouble in Big Absalom Sanctioning Document/background/Hookclaw Digger.json","Elements of Creation|LOHh|":"data/core/Lost Omens_ Highhelm/relicGift/Elements of Creation.json","Tomb Born|BotD|":"data/core/Book of the Dead/background/Tomb Born.json","Wounded|CRB|":"data/core/Core Rulebook/condition/Wounded.json","Acolyte|CRB|":"data/core/Core Rulebook/background/Acolyte.json","Perception|CRB|":"data/core/Core Rulebook/skill/Perception.json","Unremarkable|LOFb|":"data/core/Lost Omens_ Firebrands/background/Unremarkable.json","Mammoth Herder|QFF0|":"data/core/Quest for the Frozen Flame Player's Guide/background/Mammoth Herder.json","Ghlaunder|LOGM-WS|":"data/core/Lost Omens_ Gods & Magic Web Supplement/divineIntercession/Ghlaunder.json","Martial Disciple|CRB|":"data/core/Core Rulebook/background/Martial Disciple.json","Ethereal|CRB|":"data/core/Core Rulebook/relicGift/Ethereal.json","Disrupting|CRB|":"data/core/Core Rulebook/relicGift/Disrupting.json","Harrow-led|AoE4|":"data/core/Agents of Edgewatch #4_ Assault on Hunting Lodge Seven/background/Harrow-led.json","Greater Energy-Resistant|CRB|Acid":"data/core/Core Rulebook/relicGift/Greater Energy-Resistant - Acid.json","Sponsored By A Stranger|SoT0|":"data/core/Strength of Thousands Player's Guide/background/Sponsored By A Stranger.json","Wounding|CRB|":"data/core/Core Rulebook/relicGift/Wounding.json","Clan Associate|SKT0|":"data/core/Sky King's Tomb Player's Guide/background/Clan Associate.json","Belkzen Slayer|LOWG|":"data/core/Lost Omens_ World Guide/background/Belkzen Slayer.json","Necromancer's Apprentice|BotD|":"data/core/Book of the Dead/background/Necromancer's Apprentice.json","Returned|APG|":"data/core/Advanced Player's Guide/background/Returned.json","Clumsy|CRB|":"data/core/Core Rulebook/condition/Clumsy.json","Angelic Vessel|GMG|":"data/core/Gamemastery Guide/relicGift/Angelic Vessel.json","Unholy|CRB|":"data/core/Core Rulebook/relicGift/Unholy.json","Barrister|CRB|":"data/core/Core Rulebook/background/Barrister.json","Persistent Damage|CRB|":"data/core/Core Rulebook/condition/Persistent Damage.json","Sodden Scavenger|LOWG|":"data/core/Lost Omens_ World Guide/background/Sodden Scavenger.json","Child Of Westcrown|LOWG|":"data/core/Lost Omens_ World Guide/background/Child Of Westcrown.json","Mechanic|GaG|":"data/core/Guns & Gears/background/Mechanic.json","Lumber Consortium Laborer|LOWG|":"data/core/Lost Omens_ World Guide/background/Lumber Consortium Laborer.json","Grim Specter|GMG|":"data/core/Gamemastery Guide/relicGift/Grim Specter.json","Nocticula|LOGM-WS|":"data/core/Lost Omens_ Gods & Magic Web Supplement/divineIntercession/Nocticula.json","Temporal Pulse|TV|":"data/core/Treasure Vault/relicGift/Temporal Pulse.json","Osprey Fisher|Rust|":"data/core/Rusthenge/background/Osprey Fisher.json","Divine Retribution|GMG|":"data/core/Gamemastery Guide/relicGift/Divine Retribution.json","Alkenstar Sojourner|GaG|":"data/core/Guns & Gears/background/Alkenstar Sojourner.json","Magical Experiment|SoM|":"data/core/Secrets of Magic/background/Magical Experiment.json","Ruby Phoenix Fanatic|FRP0|":"data/core/Fists of the Ruby Phoenix Player's Guide/background/Ruby Phoenix Fanatic.json","Artist|CRB|":"data/core/Core Rulebook/background/Artist.json","Absorb Injury|SoM|":"data/core/Secrets of Magic/relicGift/Absorb Injury.json","Circuit Judge|GaG|":"data/core/Guns & Gears/background/Circuit Judge.json","Curse Wound|GMG|":"data/core/Gamemastery Guide/relicGift/Curse Wound.json","Spotter|GaG|":"data/core/Guns & Gears/background/Spotter.json","Elementally Infused|RoE|":"data/core/Rage of Elements/background/Elementally Infused.json","Bookish Providence|SF0|":"data/core/Stolen Fate Player's Guide/background/Bookish Providence.json","Starwatcher|AV0|":"data/core/Abomination Vaults Player's Guide/background/Starwatcher.json","Chaldira|LOGM-WS|":"data/core/Lost Omens_ Gods & Magic Web Supplement/divineIntercession/Chaldira.json","Shelyn|LOGM|":"data/core/Lost Omens_ Gods & Magic/divineIntercession/Shelyn.json","Out-of-Towner|AoA0|":"data/core/Age of Ashes Player's Guide/background/Out-of-Towner.json","Energy-Resistant|CRB|Acid":"data/core/Core Rulebook/relicGift/Energy-Resistant - Acid.json","Acrobat|CRB|":"data/core/Core Rulebook/background/Acrobat.json","Thundering|CRB|":"data/core/Core Rulebook/relicGift/Thundering.json","Pollen Spray|GMG|":"data/core/Gamemastery Guide/relicGift/Pollen Spray.json","Wind Barrier|GMG|":"data/core/Gamemastery Guide/relicGift/Wind Barrier.json","Detective|CRB|":"data/core/Core Rulebook/background/Detective.json","Emotion Conduit|TV|":"data/core/Treasure Vault/relicGift/Emotion Conduit.json","Local Scion|AoA0|":"data/core/Age of Ashes Player's Guide/background/Local Scion.json","Ustalavic Academic|LOWG|":"data/core/Lost Omens_ World Guide/background/Ustalavic Academic.json","Shielded Fortune|SF0|":"data/core/Stolen Fate Player's Guide/background/Shielded Fortune.json","Holy Light|GMG|":"data/core/Gamemastery Guide/relicGift/Holy Light.json","Osirionologist|LOWG|":"data/core/Lost Omens_ World Guide/background/Osirionologist.json","Herbalist|CRB|":"data/core/Core Rulebook/background/Herbalist.json","Pathfinder Hopeful|LOWG|":"data/core/Lost Omens_ World Guide/background/Pathfinder Hopeful.json","Tar K'hala|SolthesiaAG|":"data/homebrew/Solthesia Adventure Guide/divineIntercession/Tar K'hala.json","Inextinguishable|GMG|":"data/core/Gamemastery Guide/relicGift/Inextinguishable.json","Mystic Tutor|SoM|":"data/core/Secrets of Magic/background/Mystic Tutor.json","Quickened|CRB|":"data/core/Core Rulebook/condition/Quickened.json","Dragon Scholar|AoA0|":"data/core/Age of Ashes Player's Guide/background/Dragon Scholar.json","Tide of Death|GMG|":"data/core/Gamemastery Guide/relicGift/Tide of Death.json","Life Everlasting|GMG|":"data/core/Gamemastery Guide/relicGift/Life Everlasting.json","Gunsmith|GaG|":"data/core/Guns & Gears/background/Gunsmith.json","Willowshore Urchin|SoG0|":"data/core/Season of Ghosts Player's Guide/background/Willowshore Urchin.json","V'rar|SolthesiaAG|":"data/homebrew/Solthesia Adventure Guide/divineIntercession/V'rar.json","Medicinal Clocksmith|GaG|":"data/core/Guns & Gears/background/Medicinal Clocksmith.json","Little Helper|GMG|":"data/core/Gamemastery Guide/relicGift/Little Helper.json","Astrological Augur|LOTG|":"data/core/Lost Omens_ Travel Guide/background/Astrological Augur.json","Trailblazer|LOPSG|":"data/core/Lost Omens_ Pathfinder Society Guide/background/Trailblazer.json","Energy-Resistant|CRB|Fire":"data/core/Core Rulebook/relicGift/Energy-Resistant - Fire.json","Dreams of Vengeance|Gwrs0|":"data/core/Gatewalkers Player's Guide/background/Dreams of Vengeance.json","Vital Siphon|GMG|":"data/core/Gamemastery Guide/relicGift/Vital Siphon.json","Psychic Scream|GMG|":"data/core/Gamemastery Guide/relicGift/Psychic Scream.json","Wonder Taster|LOWG|":"data/core/Lost Omens_ World Guide/background/Wonder Taster.json","Pathfinder Recruiter|LOPSG|":"data/core/Lost Omens_ Pathfinder Society Guide/background/Pathfinder Recruiter.json","Sign Bound|LOTG|":"data/core/Lost Omens_ Travel Guide/background/Sign Bound.json","Arazni|LOGM-WS|":"data/core/Lost Omens_ Gods & Magic Web Supplement/divineIntercession/Arazni.json","Cleanse Soul|SoM|":"data/core/Secrets of Magic/relicGift/Cleanse Soul.json","Northland Forager|QFF0|":"data/core/Quest for the Frozen Flame Player's Guide/background/Northland Forager.json","Haunting Vision|AoA0|":"data/core/Age of Ashes Player's Guide/background/Haunting Vision.json","Track of the Beast|GMG|":"data/core/Gamemastery Guide/relicGift/Track of the Beast.json","Propelling Winds|GMG|":"data/core/Gamemastery Guide/relicGift/Propelling Winds.json","Fiendish Defiance|GMG|":"data/core/Gamemastery Guide/relicGift/Fiendish Defiance.json","Kalistrade Follower|LOWG|":"data/core/Lost Omens_ World Guide/background/Kalistrade Follower.json","Wanted Witness|OoA0|":"data/core/Outlaws of Alkenstar Player's Guide/background/Wanted Witness.json","Mana Wastes Refugee|LOWG|":"data/core/Lost Omens_ World Guide/background/Mana Wastes Refugee.json","Concordance Researcher|RoE|":"data/core/Rage of Elements/background/Concordance Researcher.json","Against All Odds|TV|":"data/core/Treasure Vault/relicGift/Against All Odds.json","Vohis-om-vire|SolthesiaAG|":"data/homebrew/Solthesia Adventure Guide/divineIntercession/Vohis-om-vire.json","Deep-Sea Diver|RoE|":"data/core/Rage of Elements/background/Deep-Sea Diver.json","Obscure|GMG|":"data/core/Gamemastery Guide/relicGift/Obscure.json","Toymaker|GaG|":"data/core/Guns & Gears/background/Toymaker.json","Cursed|APG|":"data/core/Advanced Player's Guide/background/Cursed.json","Thassilonian Traveler|LOWG|":"data/core/Lost Omens_ World Guide/background/Thassilonian Traveler.json","Dauntless|LOFb|":"data/core/Lost Omens_ Firebrands/background/Dauntless.json","Highborn Snoop|LOHh|":"data/core/Lost Omens_ Highhelm/background/Highborn Snoop.json","Historical Reenactor|SKT0|":"data/core/Sky King's Tomb Player's Guide/background/Historical Reenactor.json","Crafting|CRB|":"data/core/Core Rulebook/skill/Crafting.json","Major Shadow|CRB|":"data/core/Core Rulebook/relicGift/Major Shadow.json","Local Brigand|KmrA|":"data/core/Kingmaker/background/Local Brigand.json","Cook|APG|":"data/core/Advanced Player's Guide/background/Cook.json","Petrified|CRB|":"data/core/Core Rulebook/condition/Petrified.json","Time Traveler|SoM|":"data/core/Secrets of Magic/background/Time Traveler.json","Farmsteader|GaG|":"data/core/Guns & Gears/background/Farmsteader.json","Profane Fervor|GMG|":"data/core/Gamemastery Guide/relicGift/Profane Fervor.json","Trade Consortium Underling|LOWG|":"data/core/Lost Omens_ World Guide/background/Trade Consortium Underling.json","Discarded Duplicate|GaG|":"data/core/Guns & Gears/background/Discarded Duplicate.json","Entertainer|CRB|":"data/core/Core Rulebook/background/Entertainer.json","Molten Crucible|LOHh|":"data/core/Lost Omens_ Highhelm/relicGift/Molten Crucible.json","Nivi Rhombodazzle|LOGM-WS|":"data/core/Lost Omens_ Gods & Magic Web Supplement/divineIntercession/Nivi Rhombodazzle.json","Undersea Enthusiast|LOWG|":"data/core/Lost Omens_ World Guide/background/Undersea Enthusiast.json","Sky Rider|RoE|":"data/core/Rage of Elements/background/Sky Rider.json","Eclectic Scholar|SKT0|":"data/core/Sky King's Tomb Player's Guide/background/Eclectic Scholar.json","Stealth|CRB|":"data/core/Core Rulebook/skill/Stealth.json","Performance|CRB|":"data/core/Core Rulebook/skill/Performance.json","Command Legion|GMG|":"data/core/Gamemastery Guide/relicGift/Command Legion.json","Bibliophile|AV0|":"data/core/Abomination Vaults Player's Guide/background/Bibliophile.json","Chelish Rebel|LOWG|":"data/core/Lost Omens_ World Guide/background/Chelish Rebel.json","Aerialist|EC0|":"data/core/Extinction Curse Player's Guide/background/Aerialist.json","Exorcist|Spappz|":"data/homebrew/Spappz's Public Assortment of Miscellany/background/Exorcist.json","Observed|CRB|":"data/core/Core Rulebook/condition/Observed.json","Sarkorian Survivor|LOWG|":"data/core/Lost Omens_ World Guide/background/Sarkorian Survivor.json","Dendrologist|RoE|":"data/core/Rage of Elements/background/Dendrologist.json","Grappling Vine|GMG|":"data/core/Gamemastery Guide/relicGift/Grappling Vine.json","Warrior|CRB|":"data/core/Core Rulebook/background/Warrior.json","Helpful|CRB|":"data/core/Core Rulebook/condition/Helpful.json","Astrologer|SoM|":"data/core/Secrets of Magic/background/Astrologer.json","Great Migration|LOTG|":"data/core/Lost Omens_ Travel Guide/event/Great Migration.json","Academy Dropout|SoM|":"data/core/Secrets of Magic/background/Academy Dropout.json","Ruin Delver|AV0|":"data/core/Abomination Vaults Player's Guide/background/Ruin Delver.json","Legendary Parents|AoA6|":"data/core/Age of Ashes #6_ Broken Promises/background/Legendary Parents.json","Mechanical Symbiosis|GaG|":"data/core/Guns & Gears/background/Mechanical Symbiosis.json","Ex-con Token Guard|AoE0|":"data/core/Agents of Edgewatch Player's Guide/background/Ex-con Token Guard.json","Final Blade Survivor|LOWG|":"data/core/Lost Omens_ World Guide/background/Final Blade Survivor.json","Jet Propulsion|GMG|":"data/core/Gamemastery Guide/relicGift/Jet Propulsion.json","Healing Wave|GMG|":"data/core/Gamemastery Guide/relicGift/Healing Wave.json","Draconic Ascendance|SoM|":"data/core/Secrets of Magic/relicGift/Draconic Ascendance.json","Shroud of the Afterlife|GMG|":"data/core/Gamemastery Guide/relicGift/Shroud of the Afterlife.json","Circus Born|EC0|":"data/core/Extinction Curse Player's Guide/background/Circus Born.json","False Medium|SoM|":"data/core/Secrets of Magic/background/False Medium.json","Storm Survivor|LOWG|":"data/core/Lost Omens_ World Guide/background/Storm Survivor.json","Rovagug|LOGM|":"data/core/Lost Omens_ Gods & Magic/divineIntercession/Rovagug.json","Living Statue|GMG|":"data/core/Gamemastery Guide/relicGift/Living Statue.json","Eldritch Anatomist|AV0|":"data/core/Abomination Vaults Player's Guide/background/Eldritch Anatomist.json","Magical Misfit|SoM|":"data/core/Secrets of Magic/background/Magical Misfit.json","Genie-blessed|SoM|":"data/core/Secrets of Magic/background/Genie-blessed.json","Bonuwat Wavetouched|LOWG|":"data/core/Lost Omens_ World Guide/background/Bonuwat Wavetouched.json","Osprey Scion|Rust|":"data/core/Rusthenge/background/Osprey Scion.json","Controlled|CRB|":"data/core/Core Rulebook/condition/Controlled.json","Bottomless Reservoir|GMG|":"data/core/Gamemastery Guide/relicGift/Bottomless Reservoir.json","Issian Patriot|KmrA|":"data/core/Kingmaker/background/Issian Patriot.json","Sun Orchid Harvest|LOTG|":"data/core/Lost Omens_ Travel Guide/event/Sun Orchid Harvest.json","Quick|LOWG|":"data/core/Lost Omens_ World Guide/background/Quick.json","Wished Alive|GaG|":"data/core/Guns & Gears/background/Wished Alive.json","Rolling Geode|GMG|":"data/core/Gamemastery Guide/relicGift/Rolling Geode.json","Slowed|CRB|":"data/core/Core Rulebook/condition/Slowed.json","Fervor|TV|":"data/core/Treasure Vault/relicGift/Fervor.json","Purveyor Of The Bizarre|LOWG|":"data/core/Lost Omens_ World Guide/background/Purveyor Of The Bizarre.json","Union Representative|LOHh|":"data/core/Lost Omens_ Highhelm/background/Union Representative.json","Osprey Scout|Rust|":"data/core/Rusthenge/background/Osprey Scout.json","Droskar's Breath|LOTG|":"data/core/Lost Omens_ Travel Guide/event/Droskar's Breath.json","Onyx Trader|LOWG|":"data/core/Lost Omens_ World Guide/background/Onyx Trader.json","Rostlander|KmrA|":"data/core/Kingmaker/background/Rostlander.json","Hostile|CRB|":"data/core/Core Rulebook/condition/Hostile.json","Doomcaller|LOTG|":"data/core/Lost Omens_ Travel Guide/background/Doomcaller.json","Dolos|SolthesiaAG|":"data/homebrew/Solthesia Adventure Guide/divineIntercession/Dolos.json","Blow-in|EC0|":"data/core/Extinction Curse Player's Guide/background/Blow-in.json","Back-alley Doctor|GaG|":"data/core/Guns & Gears/background/Back-alley Doctor.json","Ripples and Waves|GMG|":"data/core/Gamemastery Guide/relicGift/Ripples and Waves.json","Song of the Deep|SoM|":"data/core/Secrets of Magic/background/Song of the Deep.json","Codebreaker|GaG|":"data/core/Guns & Gears/background/Codebreaker.json","Sands of the Hourglass|TV|":"data/core/Treasure Vault/relicGift/Sands of the Hourglass.json","Haunted Citizen|BotD|":"data/core/Book of the Dead/background/Haunted Citizen.json","Calistria|LOGM|":"data/core/Lost Omens_ Gods & Magic/divineIntercession/Calistria.json","Dominant Emotion|TV|":"data/core/Treasure Vault/relicGift/Dominant Emotion.json","Scion of Slayers|BotD|":"data/core/Book of the Dead/background/Scion of Slayers.json","Hammered by Fate|SF0|":"data/core/Stolen Fate Player's Guide/background/Hammered by Fate.json","Shadow|CRB|":"data/core/Core Rulebook/relicGift/Shadow.json","Emotion Surge|TV|":"data/core/Treasure Vault/relicGift/Emotion Surge.json","Surge Investigator|SoM|":"data/core/Secrets of Magic/background/Surge Investigator.json","Fire Warden|RoE|":"data/core/Rage of Elements/background/Fire Warden.json","Amnesiac|APG|":"data/core/Advanced Player's Guide/background/Amnesiac.json","Anti-magical|SoM|":"data/core/Secrets of Magic/background/Anti-magical.json","Major Slick|CRB|":"data/core/Core Rulebook/relicGift/Major Slick.json","Saved By Clockwork|GaG|":"data/core/Guns & Gears/background/Saved By Clockwork.json","Sickened|CRB|":"data/core/Core Rulebook/condition/Sickened.json","Ilo|SolthesiaAG|":"data/homebrew/Solthesia Adventure Guide/divineIntercession/Ilo.json","Draconic Resistance|SoM|":"data/core/Secrets of Magic/relicGift/Draconic Resistance.json","Grizzled Muckrucker|AoE0|":"data/core/Agents of Edgewatch Player's Guide/background/Grizzled Muckrucker.json","Enthralling|TV|":"data/core/Treasure Vault/relicGift/Enthralling.json","Returning|CRB|":"data/core/Core Rulebook/relicGift/Returning.json","Clockwork Researcher|GaG|":"data/core/Guns & Gears/background/Clockwork Researcher.json","Dreamer Of The Verdant Moon|EC3|":"data/core/Extinction Curse #3_ Life's Long Shadows/background/Dreamer Of The Verdant Moon.json","Eidolon Contact|SoM|":"data/core/Secrets of Magic/background/Eidolon Contact.json","Erastil|LOGM|":"data/core/Lost Omens_ Gods & Magic/divineIntercession/Erastil.json","Farmhand|CRB|":"data/core/Core Rulebook/background/Farmhand.json","Framed in Ferrous Quarter|OoA0|":"data/core/Outlaws of Alkenstar Player's Guide/background/Framed in Ferrous Quarter.json","Precognition|TV|":"data/core/Treasure Vault/relicGift/Precognition.json","Frightened|CRB|":"data/core/Core Rulebook/condition/Frightened.json","Osprey Spellcaster|Rust|":"data/core/Rusthenge/background/Osprey Spellcaster.json","Night Watch|BotD|":"data/core/Book of the Dead/background/Night Watch.json","Flowing Footsteps|GMG|":"data/core/Gamemastery Guide/relicGift/Flowing Footsteps.json","Mehi|SolthesiaAG|":"data/homebrew/Solthesia Adventure Guide/divineIntercession/Mehi.json","Cayden Cailean|LOGM|":"data/core/Lost Omens_ Gods & Magic/divineIntercession/Cayden Cailean.json","Conservator|SKT0|":"data/core/Sky King's Tomb Player's Guide/background/Conservator.json","Gladiator|CRB|":"data/core/Core Rulebook/background/Gladiator.json","Keys to Destiny|SF0|":"data/core/Stolen Fate Player's Guide/background/Keys to Destiny.json","Sivanah|LOGM-WS|":"data/core/Lost Omens_ Gods & Magic Web Supplement/divineIntercession/Sivanah.json","Underground Bounty|GMG|":"data/core/Gamemastery Guide/relicGift/Underground Bounty.json","Brigh|LOGM-WS|":"data/core/Lost Omens_ Gods & Magic Web Supplement/divineIntercession/Brigh.json","Animal Wrangler|EC0|":"data/core/Extinction Curse Player's Guide/background/Animal Wrangler.json","Holy|CRB|":"data/core/Core Rulebook/relicGift/Holy.json","Miner|CRB|":"data/core/Core Rulebook/background/Miner.json","Hounded Thief|GaG|":"data/core/Guns & Gears/background/Hounded Thief.json","Reputation Seeker|AoA0|":"data/core/Age of Ashes Player's Guide/background/Reputation Seeker.json","Desert Tracker|LOWG|":"data/core/Lost Omens_ World Guide/background/Desert Tracker.json","Squire|APG|":"data/core/Advanced Player's Guide/background/Squire.json","Charming|TV|":"data/core/Treasure Vault/relicGift/Charming.json","Greater Flaming|CRB|":"data/core/Core Rulebook/relicGift/Greater Flaming.json","Muse|TV|":"data/core/Treasure Vault/relicGift/Muse.json","Intimidation|CRB|":"data/core/Core Rulebook/skill/Intimidation.json","Force Blast|SoM|":"data/core/Secrets of Magic/relicGift/Force Blast.json","Beginner's Luck|TV|":"data/core/Treasure Vault/relicGift/Beginner's Luck.json","Waste Walker|GaG|":"data/core/Guns & Gears/background/Waste Walker.json","Sponsored By Teacher Ot|SoT0|":"data/core/Strength of Thousands Player's Guide/background/Sponsored By Teacher Ot.json","Field Medic|CRB|":"data/core/Core Rulebook/background/Field Medic.json","Ralef|SolthesiaAG|":"data/homebrew/Solthesia Adventure Guide/divineIntercession/Ralef.json","Milani|LOGM-WS|":"data/core/Lost Omens_ Gods & Magic Web Supplement/divineIntercession/Milani.json","Stunned|CRB|":"data/core/Core Rulebook/condition/Stunned.json","Heat Haze|GMG|":"data/core/Gamemastery Guide/relicGift/Heat Haze.json","Greater Fortification|CRB|":"data/core/Core Rulebook/relicGift/Greater Fortification.json","Total Power|Gwrs0|":"data/core/Gatewalkers Player's Guide/background/Total Power.json","Ward|APG|":"data/core/Advanced Player's Guide/background/Ward.json","Plant Whisperer|SoM|":"data/core/Secrets of Magic/background/Plant Whisperer.json","Fireworks Performer|GaG|":"data/core/Guns & Gears/background/Fireworks Performer.json","Alseta|LOGM-WS|":"data/core/Lost Omens_ Gods & Magic Web Supplement/divineIntercession/Alseta.json","Insurgent|APG|":"data/core/Advanced Player's Guide/background/Insurgent.json","Sponsored By Family|SoT0|":"data/core/Strength of Thousands Player's Guide/background/Sponsored By Family.json","Beast Senses|GMG|":"data/core/Gamemastery Guide/relicGift/Beast Senses.json","Merchant|CRB|":"data/core/Core Rulebook/background/Merchant.json","Droskari Disciple|AoA4|":"data/core/Age of Ashes #4_ Fires of the Haunted City/background/Droskari Disciple.json","Royalty|APG|":"data/core/Advanced Player's Guide/background/Royalty.json","Reclaimed|LOKL|":"data/core/Lost Omens_ Knights of Lastwall/background/Reclaimed.json","Rigger|EC0|":"data/core/Extinction Curse Player's Guide/background/Rigger.json","Merabite Prodigy|LOWG|":"data/core/Lost Omens_ World Guide/background/Merabite Prodigy.json","Ancestors' Call|SKT1|":"data/core/Sky King's Tomb #1_ Mantle of Gold/relicGift/Ancestors' Call.json","Enfeebled|CRB|":"data/core/Core Rulebook/condition/Enfeebled.json","Greater Shadow|CRB|":"data/core/Core Rulebook/relicGift/Greater Shadow.json","Northridge Scholar|SoG0|":"data/core/Season of Ghosts Player's Guide/background/Northridge Scholar.json","Inlander|LOWG|":"data/core/Lost Omens_ World Guide/background/Inlander.json","Seer of the Dead|SoM|":"data/core/Secrets of Magic/background/Seer of the Dead.json","Press-ganged|LOWG|":"data/core/Lost Omens_ World Guide/background/Press-ganged.json","Rivethun Adherent|LOWG|":"data/core/Lost Omens_ World Guide/background/Rivethun Adherent.json","Bookkeeper|APG|":"data/core/Advanced Player's Guide/background/Bookkeeper.json","Scout|CRB|":"data/core/Core Rulebook/background/Scout.json","Beast Blessed|LOFb|":"data/core/Lost Omens_ Firebrands/background/Beast Blessed.json","Tall Tale|GaG|":"data/core/Guns & Gears/background/Tall Tale.json","Unnoticed|CRB|":"data/core/Core Rulebook/condition/Unnoticed.json","Kazutal|LOGM-WS|":"data/core/Lost Omens_ Gods & Magic Web Supplement/divineIntercession/Kazutal.json","Flare Bolt|GMG|":"data/core/Gamemastery Guide/relicGift/Flare Bolt.json","Bright Lion|LOWG|":"data/core/Lost Omens_ World Guide/background/Bright Lion.json","Writ in the Stars|SF0|":"data/core/Stolen Fate Player's Guide/background/Writ in the Stars.json","Mammoth Speaker|LOWG|":"data/core/Lost Omens_ World Guide/background/Mammoth Speaker.json","Noble|CRB|":"data/core/Core Rulebook/background/Noble.json","Wanderlust|Gwrs0|":"data/core/Gatewalkers Player's Guide/background/Wanderlust.json","Casandalee|LOGM-WS|":"data/core/Lost Omens_ Gods & Magic Web Supplement/divineIntercession/Casandalee.json","Southbank Traditionalist|SoG0|":"data/core/Season of Ghosts Player's Guide/background/Southbank Traditionalist.json","Political Scion|AoE0|":"data/core/Agents of Edgewatch Player's Guide/background/Political Scion.json","Restrained|CRB|":"data/core/Core Rulebook/condition/Restrained.json","Musical Prodigy|SoM|":"data/core/Secrets of Magic/background/Musical Prodigy.json","Messenger Tide|LOTG|":"data/core/Lost Omens_ Travel Guide/event/Messenger Tide.json","Shadow Smith|GMG|":"data/core/Gamemastery Guide/relicGift/Shadow Smith.json","Boazandravul|SolthesiaAG|":"data/homebrew/Solthesia Adventure Guide/divineIntercession/Boazandravul.json","Bounty Hunter|CRB|":"data/core/Core Rulebook/background/Bounty Hunter.json","Money Counter|BL0|":"data/core/Blood Lords Player's Guide/background/Money Counter.json","Quickening Emotion|TV|":"data/core/Treasure Vault/relicGift/Quickening Emotion.json","Thuvian Unifier|LOWG|":"data/core/Lost Omens_ World Guide/background/Thuvian Unifier.json","Time Jump|TV|":"data/core/Treasure Vault/relicGift/Time Jump.json","Lashing Currents|GMG|":"data/core/Gamemastery Guide/relicGift/Lashing Currents.json","Able Carter|BL0|":"data/core/Blood Lords Player's Guide/background/Able Carter.json","Aspiring River Monarch|LOWG|":"data/core/Lost Omens_ World Guide/background/Aspiring River Monarch.json","Driver|GaG|":"data/core/Guns & Gears/background/Driver.json","Kurgess|LOGM-WS|":"data/core/Lost Omens_ Gods & Magic Web Supplement/divineIntercession/Kurgess.json","Intelligent Relic|TV|":"data/core/Treasure Vault/relicGift/Intelligent Relic.json","Sun Dancer|LOTG|":"data/core/Lost Omens_ Travel Guide/background/Sun Dancer.json","Desna|LOGM|":"data/core/Lost Omens_ Gods & Magic/divineIntercession/Desna.json","Naator|SolthesiaAG|":"data/homebrew/Solthesia Adventure Guide/divineIntercession/Naator.json","Shattered Earth|GMG|":"data/core/Gamemastery Guide/relicGift/Shattered Earth.json","Greater Energy-Resistant|CRB|Electricity":"data/core/Core Rulebook/relicGift/Greater Energy-Resistant - Electricity.json","Butcher|EC0|":"data/core/Extinction Curse Player's Guide/background/Butcher.json","Winter's Child|LOWG|":"data/core/Lost Omens_ World Guide/background/Winter's Child.json","Anti-tech Activist|GaG|":"data/core/Guns & Gears/background/Anti-tech Activist.json","Dvadat Zikir|SolthesiaAG|":"data/homebrew/Solthesia Adventure Guide/divineIntercession/Dvadat Zikir.json","Drained|CRB|":"data/core/Core Rulebook/condition/Drained.json","Wishes for Riches|Gwrs0|":"data/core/Gatewalkers Player's Guide/background/Wishes for Riches.json","Autumn's Reflection|LOTG|":"data/core/Lost Omens_ Travel Guide/event/Autumn's Reflection.json","Godless Graycloak|AoE0|":"data/core/Agents of Edgewatch Player's Guide/background/Godless Graycloak.json","Confused|CRB|":"data/core/Core Rulebook/condition/Confused.json","Petal Dance|GMG|":"data/core/Gamemastery Guide/relicGift/Petal Dance.json","Sense of Belonging|Gwrs0|":"data/core/Gatewalkers Player's Guide/background/Sense of Belonging.json","Creative Spark|LOHh|":"data/core/Lost Omens_ Highhelm/relicGift/Creative Spark.json","Abadar|LOGM|":"data/core/Lost Omens_ Gods & Magic/divineIntercession/Abadar.json","Clean Luck|TV|":"data/core/Treasure Vault/relicGift/Clean Luck.json","Tech-reliant|GaG|":"data/core/Guns & Gears/background/Tech-reliant.json","Hunter|CRB|":"data/core/Core Rulebook/background/Hunter.json","Athletics|CRB|":"data/core/Core Rulebook/skill/Athletics.json","Child of the Twin Village|DA|":"data/core/Dark Archive/background/Child of the Twin Village.json","Fightbreaker|LOHh|":"data/core/Lost Omens_ Highhelm/background/Fightbreaker.json","Shifting|CRB|":"data/core/Core Rulebook/relicGift/Shifting.json","Otherworldly Mission|GaG|":"data/core/Guns & Gears/background/Otherworldly Mission.json","Borrow Time|TV|":"data/core/Treasure Vault/relicGift/Borrow Time.json","Friendly|CRB|":"data/core/Core Rulebook/condition/Friendly.json","Sheriff|GaG|":"data/core/Guns & Gears/background/Sheriff.json","Bellflower Agent|LOWG|":"data/core/Lost Omens_ World Guide/background/Bellflower Agent.json","Megaflora|GMG|":"data/core/Gamemastery Guide/relicGift/Megaflora.json","Inspiring|TV|":"data/core/Treasure Vault/relicGift/Inspiring.json","Steal Luck|TV|":"data/core/Treasure Vault/relicGift/Steal Luck.json","Encumbered|CRB|":"data/core/Core Rulebook/condition/Encumbered.json","Undercover Contender|FRP0|":"data/core/Fists of the Ruby Phoenix Player's Guide/background/Undercover Contender.json","Scholar|CRB|":"data/core/Core Rulebook/background/Scholar.json","Mental Bastion|GMG|":"data/core/Gamemastery Guide/relicGift/Mental Bastion.json","Incandescent Sight|GMG|":"data/core/Gamemastery Guide/relicGift/Incandescent Sight.json","Aspiring Free Captain|LOWG|":"data/core/Lost Omens_ World Guide/background/Aspiring Free Captain.json","Street Urchin|CRB|":"data/core/Core Rulebook/background/Street Urchin.json","Glacial Whirl|LOTG|":"data/core/Lost Omens_ Travel Guide/event/Glacial Whirl.json","Flat-Footed|CRB|":"data/core/Core Rulebook/condition/Flat-Footed.json","Child of Notoriety|SKT0|":"data/core/Sky King's Tomb Player's Guide/background/Child of Notoriety.json","Pierce the Veil|GMG|":"data/core/Gamemastery Guide/relicGift/Pierce the Veil.json","Ulfen Raider|LOWG|":"data/core/Lost Omens_ World Guide/background/Ulfen Raider.json","Time Reversal|TV|":"data/core/Treasure Vault/relicGift/Time Reversal.json","Deception|CRB|":"data/core/Core Rulebook/skill/Deception.json","Saloon Entertainer|GaG|":"data/core/Guns & Gears/background/Saloon Entertainer.json","Secular Medic|LOWG|":"data/core/Lost Omens_ World Guide/background/Secular Medic.json","Child Of The Puddles|LOWG|":"data/core/Lost Omens_ World Guide/background/Child Of The Puddles.json","Torag|LOGM|":"data/core/Lost Omens_ Gods & Magic/divineIntercession/Torag.json","Diobel Pearl Diver|LOWG|":"data/core/Lost Omens_ World Guide/background/Diobel Pearl Diver.json","Close Ties|SoG0|":"data/core/Season of Ghosts Player's Guide/background/Close Ties.json","Banished Brighite|OoA0|":"data/core/Outlaws of Alkenstar Player's Guide/background/Banished Brighite.json","Nexian Mystic|LOWG|":"data/core/Lost Omens_ World Guide/background/Nexian Mystic.json","Fortification|CRB|":"data/core/Core Rulebook/relicGift/Fortification.json","Unumaator|SolthesiaAG|":"data/homebrew/Solthesia Adventure Guide/divineIntercession/Unumaator.json","Harbor Guard Moonlighter|AoE0|":"data/core/Agents of Edgewatch Player's Guide/background/Harbor Guard Moonlighter.json","Ozem Experience|LOKL|":"data/core/Lost Omens_ Knights of Lastwall/background/Ozem Experience.json","Revenant|GaG|":"data/core/Guns & Gears/background/Revenant.json","Soul Magic|SoM|":"data/core/Secrets of Magic/relicGift/Soul Magic.json","Reclaimer Investigator|LOKL|":"data/core/Lost Omens_ Knights of Lastwall/background/Reclaimer Investigator.json","Inexplicably Expelled|OoA0|":"data/core/Outlaws of Alkenstar Player's Guide/background/Inexplicably Expelled.json","Anarchic|CRB|":"data/core/Core Rulebook/relicGift/Anarchic.json","Greater Shock|CRB|":"data/core/Core Rulebook/relicGift/Greater Shock.json","Pillar|LOKL|":"data/core/Lost Omens_ Knights of Lastwall/background/Pillar.json","Goblinblood Orphan|LOWG|":"data/core/Lost Omens_ World Guide/background/Goblinblood Orphan.json","Bandit|APG|":"data/core/Advanced Player's Guide/background/Bandit.json","Laborer|CRB|":"data/core/Core Rulebook/background/Laborer.json","Menagerie Dung Sweeper|LOWG|":"data/core/Lost Omens_ World Guide/background/Menagerie Dung Sweeper.json","Death Gaze|GMG|":"data/core/Gamemastery Guide/relicGift/Death Gaze.json","Indifferent|CRB|":"data/core/Core Rulebook/condition/Indifferent.json","Lastwall Survivor|LOWG|":"data/core/Lost Omens_ World Guide/background/Lastwall Survivor.json","Witch Wary|LOWG|":"data/core/Lost Omens_ World Guide/background/Witch Wary.json","Shizuru|LOGM-WS|":"data/core/Lost Omens_ Gods & Magic Web Supplement/divineIntercession/Shizuru.json","Curandero|BotD|":"data/core/Book of the Dead/background/Curandero.json","Megafauna Hunter|QFF0|":"data/core/Quest for the Frozen Flame Player's Guide/background/Megafauna Hunter.json","Crystal Healer|RoE|":"data/core/Rage of Elements/background/Crystal Healer.json","Gambler|CRB|":"data/core/Core Rulebook/background/Gambler.json","Searing Wave|GMG|":"data/core/Gamemastery Guide/relicGift/Searing Wave.json","Besmara|LOGM-WS|":"data/core/Lost Omens_ Gods & Magic Web Supplement/divineIntercession/Besmara.json","Guard|CRB|":"data/core/Core Rulebook/background/Guard.json","Tidal Crash|GMG|":"data/core/Gamemastery Guide/relicGift/Tidal Crash.json","Thievery|CRB|":"data/core/Core Rulebook/skill/Thievery.json","Food Trader|BL0|":"data/core/Blood Lords Player's Guide/background/Food Trader.json","Axiomatic|CRB|":"data/core/Core Rulebook/relicGift/Axiomatic.json","Quick Refugee|C-WtD2|":"data/core/Wake the Dead #2/background/Quick Refugee.json","Oenopion Ooze-tender|LOWG|":"data/core/Lost Omens_ World Guide/background/Oenopion Ooze-tender.json","Archaeologist|LOPSG|":"data/core/Lost Omens_ Pathfinder Society Guide/background/Archaeologist.json","Sailor|CRB|":"data/core/Core Rulebook/background/Sailor.json","Outrider|APG|":"data/core/Advanced Player's Guide/background/Outrider.json","Bekyar Restorer|LOWG|":"data/core/Lost Omens_ World Guide/background/Bekyar Restorer.json","Rail Dash|RoE|":"data/core/Rage of Elements/relicGift/Rail Dash.json","Prisoner|CRB|":"data/core/Core Rulebook/background/Prisoner.json","Molthuni Mercenary|LOWG|":"data/core/Lost Omens_ World Guide/background/Molthuni Mercenary.json","Lore|CRB|":"data/core/Core Rulebook/skill/Lore.json","Feather Steps|GMG|":"data/core/Gamemastery Guide/relicGift/Feather Steps.json","Fervent Spell|TV|":"data/core/Treasure Vault/relicGift/Fervent Spell.json","Lost Loved One|Gwrs0|":"data/core/Gatewalkers Player's Guide/background/Lost Loved One.json","Energy Scarred|SoM|":"data/core/Secrets of Magic/background/Energy Scarred.json","Precious Anodization|RoE|":"data/core/Rage of Elements/relicGift/Precious Anodization.json","Groetus|LOGM-WS|":"data/core/Lost Omens_ Gods & Magic Web Supplement/divineIntercession/Groetus.json","Willing Host|BotD|":"data/core/Book of the Dead/background/Willing Host.json","Fascinated|CRB|":"data/core/Core Rulebook/condition/Fascinated.json","Servant|APG|":"data/core/Advanced Player's Guide/background/Servant.json","Osprey Barnraiser|Rust|":"data/core/Rusthenge/background/Osprey Barnraiser.json","Fiendish Bargain|GMG|":"data/core/Gamemastery Guide/relicGift/Fiendish Bargain.json","Shock|CRB|":"data/core/Core Rulebook/relicGift/Shock.json","Brevic Outcast|KmrA|":"data/core/Kingmaker/background/Brevic Outcast.json","Cursed Family|LOWG|":"data/core/Lost Omens_ World Guide/background/Cursed Family.json","Encompassing Darkness|GMG|":"data/core/Gamemastery Guide/relicGift/Encompassing Darkness.json","Forge Weld|LOHh|":"data/core/Lost Omens_ Highhelm/relicGift/Forge Weld.json","Goldhand Arms Dealer|GaG|":"data/core/Guns & Gears/background/Goldhand Arms Dealer.json","Blinded|CRB|":"data/core/Core Rulebook/condition/Blinded.json","Thrune Loyalist|LOWG|":"data/core/Lost Omens_ World Guide/background/Thrune Loyalist.json","Barber|APG|":"data/core/Advanced Player's Guide/background/Barber.json","Tsukiyo|LOGM-WS|":"data/core/Lost Omens_ Gods & Magic Web Supplement/divineIntercession/Tsukiyo.json","Work Harden|LOHh|":"data/core/Lost Omens_ Highhelm/relicGift/Work Harden.json","Eclipseborn|LOTG|":"data/core/Lost Omens_ Travel Guide/background/Eclipseborn.json","Norgorber|LOGM|":"data/core/Lost Omens_ Gods & Magic/divineIntercession/Norgorber.json","Artisan|CRB|":"data/core/Core Rulebook/background/Artisan.json","Street Preacher|SoM|":"data/core/Secrets of Magic/background/Street Preacher.json","Teacher|APG|":"data/core/Advanced Player's Guide/background/Teacher.json","Dzafur|SolthesiaAG|":"data/homebrew/Solthesia Adventure Guide/divineIntercession/Dzafur.json","Razmiran Faithful|LOWG|":"data/core/Lost Omens_ World Guide/background/Razmiran Faithful.json","Hermit|CRB|":"data/core/Core Rulebook/background/Hermit.json","Deafened|CRB|":"data/core/Core Rulebook/condition/Deafened.json","Barker|EC0|":"data/core/Extinction Curse Player's Guide/background/Barker.json","Broken|CRB|":"data/core/Core Rulebook/condition/Broken.json","Feral Child|APG|":"data/core/Advanced Player's Guide/background/Feral Child.json","Spell Seeker|LOPSG|":"data/core/Lost Omens_ Pathfinder Society Guide/background/Spell Seeker.json","Pilgrim|APG|":"data/core/Advanced Player's Guide/background/Pilgrim.json","Grabbed|CRB|":"data/core/Core Rulebook/condition/Grabbed.json","Mystic Seer|EC0|":"data/core/Extinction Curse Player's Guide/background/Mystic Seer.json","Occultism|CRB|":"data/core/Core Rulebook/skill/Occultism.json","Gorum|LOGM|":"data/core/Lost Omens_ Gods & Magic/divineIntercession/Gorum.json","Wyrm's Flight|SoM|":"data/core/Secrets of Magic/relicGift/Wyrm's Flight.json","Aiudara Seeker|AoA6|":"data/core/Age of Ashes #6_ Broken Promises/background/Aiudara Seeker.json","Emancipated|AoA0|":"data/core/Age of Ashes Player's Guide/background/Emancipated.json","Sword Scion|KmrA|":"data/core/Kingmaker/background/Sword Scion.json","Shadow Haunted|LOWG|":"data/core/Lost Omens_ World Guide/background/Shadow Haunted.json","Wildwood Local|LOWG|":"data/core/Lost Omens_ World Guide/background/Wildwood Local.json","Osprey Scribe|Rust|":"data/core/Rusthenge/background/Osprey Scribe.json","Touched By Dahak|AoA6|":"data/core/Age of Ashes #6_ Broken Promises/background/Touched By Dahak.json","Blazing Soul|GMG|":"data/core/Gamemastery Guide/relicGift/Blazing Soul.json","Dancing|CRB|":"data/core/Core Rulebook/relicGift/Dancing.json","Criminal|CRB|":"data/core/Core Rulebook/background/Criminal.json","Prone|CRB|":"data/core/Core Rulebook/condition/Prone.json","Doomed|CRB|":"data/core/Core Rulebook/condition/Doomed.json","Newcomer In Need|FRP0|":"data/core/Fists of the Ruby Phoenix Player's Guide/background/Newcomer In Need.json","Osprey Warrior|Rust|":"data/core/Rusthenge/background/Osprey Warrior.json","Dedicated Delver|SKT0|":"data/core/Sky King's Tomb Player's Guide/background/Dedicated Delver.json","Market Runner|AV0|":"data/core/Abomination Vaults Player's Guide/background/Market Runner.json","Borderlands Pioneer|KmrA|":"data/core/Kingmaker/background/Borderlands Pioneer.json","Whispering Way Scion|LOWG|":"data/core/Lost Omens_ World Guide/background/Whispering Way Scion.json","Scholar Of The Ancients|LOWG|":"data/core/Lost Omens_ World Guide/background/Scholar Of The Ancients.json","At Will Decay|RoE|":"data/core/Rage of Elements/relicGift/At Will Decay.json","Issian Partisan|LOWG|":"data/core/Lost Omens_ World Guide/background/Issian Partisan.json","Varisian Wanderer|LOWG|":"data/core/Lost Omens_ World Guide/background/Varisian Wanderer.json","Saboteur|GaG|":"data/core/Guns & Gears/background/Saboteur.json","Ease Burden|GMG|":"data/core/Gamemastery Guide/relicGift/Ease Burden.json","Alloysmith|RoE|":"data/core/Rage of Elements/background/Alloysmith.json","Diplomacy|CRB|":"data/core/Core Rulebook/skill/Diplomacy.json","Unfriendly|CRB|":"data/core/Core Rulebook/condition/Unfriendly.json","Courier|APG|":"data/core/Advanced Player's Guide/background/Courier.json","Witchlight Follower|AV0|":"data/core/Abomination Vaults Player's Guide/background/Witchlight Follower.json","Snubbed Out Stoolie|OoA0|":"data/core/Outlaws of Alkenstar Player's Guide/background/Snubbed Out Stoolie.json","Dying|CRB|":"data/core/Core Rulebook/condition/Dying.json","Gruhastha|LOGM-WS|":"data/core/Lost Omens_ Gods & Magic Web Supplement/divineIntercession/Gruhastha.json","Alkenstar Tinker|LOWG|":"data/core/Lost Omens_ World Guide/background/Alkenstar Tinker.json","Slick|CRB|":"data/core/Core Rulebook/relicGift/Slick.json","Overflowing Life|GMG|":"data/core/Gamemastery Guide/relicGift/Overflowing Life.json","Form of Fury|GMG|":"data/core/Gamemastery Guide/relicGift/Form of Fury.json","Abadar's Avenger|FRP0|":"data/core/Fists of the Ruby Phoenix Player's Guide/background/Abadar's Avenger.json","Ratted-Out Gun Runner|OoA0|":"data/core/Outlaws of Alkenstar Player's Guide/background/Ratted-Out Gun Runner.json","Linguistic Nexus|GMG|":"data/core/Gamemastery Guide/relicGift/Linguistic Nexus.json","Fatigued|CRB|":"data/core/Core Rulebook/condition/Fatigued.json","Artistic Perfection|TV|":"data/core/Treasure Vault/relicGift/Artistic Perfection.json","Dazzled|CRB|":"data/core/Core Rulebook/condition/Dazzled.json","Tinker|CRB|":"data/core/Core Rulebook/background/Tinker.json","Student Of Magic|SoM|":"data/core/Secrets of Magic/background/Student Of Magic.json","Deadly Spark|GMG|":"data/core/Gamemastery Guide/relicGift/Deadly Spark.json","Survival|CRB|":"data/core/Core Rulebook/skill/Survival.json","Runner|LOFb|":"data/core/Lost Omens_ Firebrands/background/Runner.json","Feybound|APG|":"data/core/Advanced Player's Guide/background/Feybound.json","Nocturnal Navigator|LOTG|":"data/core/Lost Omens_ Travel Guide/background/Nocturnal Navigator.json","Pyre Tender|BotD|":"data/core/Book of the Dead/background/Pyre Tender.json","Righteous Call|GMG|":"data/core/Gamemastery Guide/relicGift/Righteous Call.json","Nomad|CRB|":"data/core/Core Rulebook/background/Nomad.json","Scrap Shot|RoE|":"data/core/Rage of Elements/relicGift/Scrap Shot.json","Corpse Stitcher|BL0|":"data/core/Blood Lords Player's Guide/background/Corpse Stitcher.json","Free Spirit|LOFb|":"data/core/Lost Omens_ Firebrands/background/Free Spirit.json","Kyonin Emissary|LOWG|":"data/core/Lost Omens_ World Guide/background/Kyonin Emissary.json","Nature|CRB|":"data/core/Core Rulebook/skill/Nature.json","Charlatan|CRB|":"data/core/Core Rulebook/background/Charlatan.json","Printer|GaG|":"data/core/Guns & Gears/background/Printer.json","Hidden|CRB|":"data/core/Core Rulebook/condition/Hidden.json","Lamashtu|LOGM|":"data/core/Lost Omens_ Gods & Magic/divineIntercession/Lamashtu.json","Tax Collector|APG|":"data/core/Advanced Player's Guide/background/Tax Collector.json","Immobilized|CRB|":"data/core/Core Rulebook/condition/Immobilized.json","Sleepless Suns Star|AoE0|":"data/core/Agents of Edgewatch Player's Guide/background/Sleepless Suns Star.json","Achaekek|LOGM-WS|":"data/core/Lost Omens_ Gods & Magic Web Supplement/divineIntercession/Achaekek.json","Umbral Body|GMG|":"data/core/Gamemastery Guide/relicGift/Umbral Body.json","Junk Collector|GaG|":"data/core/Guns & Gears/background/Junk Collector.json","Construction Occultist|BL0|":"data/core/Blood Lords Player's Guide/background/Construction Occultist.json","Vidrian Reformer|LOWG|":"data/core/Lost Omens_ World Guide/background/Vidrian Reformer.json","Draconic Arrogance|SoM|":"data/core/Secrets of Magic/relicGift/Draconic Arrogance.json","Bestow Life|GMG|":"data/core/Gamemastery Guide/relicGift/Bestow Life.json","Cannoneer|GaG|":"data/core/Guns & Gears/background/Cannoneer.json","Folklore Enthusiast|SoG0|":"data/core/Season of Ghosts Player's Guide/background/Folklore Enthusiast.json","Undercover Lotus Guard|AoE0|":"data/core/Agents of Edgewatch Player's Guide/background/Undercover Lotus Guard.json","Deputy|GaG|":"data/core/Guns & Gears/background/Deputy.json","Nethys|LOGM|":"data/core/Lost Omens_ Gods & Magic/divineIntercession/Nethys.json","Raised by Belief|LOGM|":"data/core/Lost Omens_ Gods & Magic/background/Raised by Belief.json","Sponsored By A Village|SoT0|":"data/core/Strength of Thousands Player's Guide/background/Sponsored By A Village.json","Form of Vengeance|GMG|":"data/core/Gamemastery Guide/relicGift/Form of Vengeance.json","Unsponsored|SoT0|":"data/core/Strength of Thousands Player's Guide/background/Unsponsored.json","Fogfen Tale-teller|AV0|":"data/core/Abomination Vaults Player's Guide/background/Fogfen Tale-teller.json","Irori|LOGM|":"data/core/Lost Omens_ Gods & Magic/divineIntercession/Irori.json","Acrobatics|CRB|":"data/core/Core Rulebook/skill/Acrobatics.json","Shory Seeker|LOWG|":"data/core/Lost Omens_ World Guide/background/Shory Seeker.json","Disciple Of The Gear|GaG|":"data/core/Guns & Gears/background/Disciple Of The Gear.json","Dancing Shadow|GMG|":"data/core/Gamemastery Guide/relicGift/Dancing Shadow.json","Starless One|LOTG|":"data/core/Lost Omens_ Travel Guide/background/Starless One.json","Soul Puppet|SoM|":"data/core/Secrets of Magic/relicGift/Soul Puppet.json","Ghost Touch|CRB|":"data/core/Core Rulebook/relicGift/Ghost Touch.json","Tyrant Witness|LOKL|":"data/core/Lost Omens_ Knights of Lastwall/background/Tyrant Witness.json","Crown of Chaos|SF0|":"data/core/Stolen Fate Player's Guide/background/Crown of Chaos.json","Undertaker|GaG|":"data/core/Guns & Gears/background/Undertaker.json","Tide Watcher|LOTG|":"data/core/Lost Omens_ Travel Guide/background/Tide Watcher.json","Swap Luck|TV|":"data/core/Treasure Vault/relicGift/Swap Luck.json","Call of the Wild|GMG|":"data/core/Gamemastery Guide/relicGift/Call of the Wild.json","Refugee|APG|":"data/core/Advanced Player's Guide/background/Refugee.json","Post Guard Of All Trades|AoE0|":"data/core/Agents of Edgewatch Player's Guide/background/Post Guard Of All Trades.json","Magical Merchant|SoM|":"data/core/Secrets of Magic/background/Magical Merchant.json","Learned Guard Prodigy|AoE0|":"data/core/Agents of Edgewatch Player's Guide/background/Learned Guard Prodigy.json","Monsoon Curtain|GMG|":"data/core/Gamemastery Guide/relicGift/Monsoon Curtain.json","Living Storm|GMG|":"data/core/Gamemastery Guide/relicGift/Living Storm.json","Perfection Seeker|LOWG|":"data/core/Lost Omens_ World Guide/background/Perfection Seeker.json","Black Market Smuggler|LOWG|":"data/core/Lost Omens_ World Guide/background/Black Market Smuggler.json","Raise Ramparts|GMG|":"data/core/Gamemastery Guide/relicGift/Raise Ramparts.json","Recalculate|GMG|":"data/core/Gamemastery Guide/relicGift/Recalculate.json","Press-ganged|GaG|":"data/core/Guns & Gears/background/Press-ganged.json","Hei Feng|LOGM-WS|":"data/core/Lost Omens_ Gods & Magic Web Supplement/divineIntercession/Hei Feng.json","Invisibility|CRB|":"data/core/Core Rulebook/relicGift/Invisibility.json","Alkenstar Outlaw|GaG|":"data/core/Guns & Gears/background/Alkenstar Outlaw.json","Returning Descendant|AoA0|":"data/core/Age of Ashes Player's Guide/background/Returning Descendant.json","Reborn Soul|DA|":"data/core/Dark Archive/background/Reborn Soul.json","Translator|LOPSG|":"data/core/Lost Omens_ Pathfinder Society Guide/background/Translator.json","Hellknight Historian|AoA0|":"data/core/Age of Ashes Player's Guide/background/Hellknight Historian.json","Atteran Rancher|LOWG|":"data/core/Lost Omens_ World Guide/background/Atteran Rancher.json","Breath of Dragons|SoM|":"data/core/Secrets of Magic/relicGift/Breath of Dragons.json","Second Chance Champion|FRP0|":"data/core/Fists of the Ruby Phoenix Player's Guide/background/Second Chance Champion.json","Once Bitten|LOKL|":"data/core/Lost Omens_ Knights of Lastwall/background/Once Bitten.json","Nirmathi Guerrilla|LOWG|":"data/core/Lost Omens_ World Guide/background/Nirmathi Guerrilla.json","Magaambya Academic|LOWG|":"data/core/Lost Omens_ World Guide/background/Magaambya Academic.json","Firebrand Follower|LOFb|":"data/core/Lost Omens_ Firebrands/background/Firebrand Follower.json","Greater Energy-Resistant|CRB|Fire":"data/core/Core Rulebook/relicGift/Greater Energy-Resistant - Fire.json","Greater Thundering|CRB|":"data/core/Core Rulebook/relicGift/Greater Thundering.json"}
