{
	"type": "background",
	"name": {
		"primary": "Alkenstar Sojourner"
	},
	"source": {
		"page": 124,
		"ID": "GaG"
	},
	"data": {
		"traits": [
			{
				"trait": "uncommon"
			}
		],
		"entries": [
			"You came to Alkenstar because you heard they had guns, but you stayed because of the atmosphere. Or the guns.",
			"Either way, journalism and scientific curiosity opened the door to a life of adventure. Now you continue to adventure in the Alkenstar area, using your skills to deal with whatever situations present themselves.",
			"Choose two ability boosts. One must be to Intelligence or Charisma, and one is a free ability boost.",
			"You're trained in {@skill Society} and {@skill Lore||Engineering Lore}. You gain the {@feat Streetwise} skill feat."
		]
	},
	"tags": {
		"abilityBoosts": {
			"count": 2,
			"abilities": {
				"Intelligence": true,
				"Charisma": true,
				"Free": true
			}
		},
		"trainedSkills": {
			"count": 2,
			"skills": {
				"Society": true,
				"Lore": true
			}
		},
		"gainedFeats": {
			"count": 1,
			"options": [
				{
					"name": "Streetwise",
					"sourceID": "CRB"
				}
			]
		}
	}
}
