{
	"type": "background",
	"name": {
		"primary": "Inlander"
	},
	"source": {
		"page": 22,
		"ID": "LOWG"
	},
	"data": {
		"entries": [
			"You grew up in an untamed region of the Isle of Kortos, and you know how to survive in the wild.",
			"Choose two ability boosts. One must be to Constitution or Wisdom, and one is a free ability boost.",
			"You're trained in the {@skill Survival} skill and a {@skill Lore} skill related to the terrain type associated with your home region (such as {@skill Lore||Hills Lore} or {@skill Lore||Mountains Lore}). You gain the {@feat Survey Wildlife} skill feat."
		],
		"_tags": {
			"abilityBoosts": {
				"count": 2,
				"abilities": {
					"Constitution": true,
					"Wisdom": true,
					"free": true
				}
			},
			"trainedSkills": {
				"count": 2,
				"skills": {
					"Survival": true,
					"Lore": true
				}
			},
			"gainedFeats": {
				"count": 1,
				"options": [
					{
						"name": "Survey Wildlife",
						"sourceID": "CRB"
					}
				]
			}
		}
	}
}
